flipy/__init__.py
flipy/lp_constraint.py
flipy/lp_expression.py
flipy/lp_objective.py
flipy/lp_problem.py
flipy/lp_reader.py
flipy/lp_variable.py
flipy/utils.py
flipy/flipy/__init__.py
flipy/flipy/lp_constraint.py
flipy/flipy/lp_expression.py
flipy/flipy/lp_objective.py
flipy/flipy/lp_problem.py
flipy/flipy/lp_reader.py
flipy/flipy/lp_variable.py
flipy/flipy/utils.py
flipy/flipy/flipy/__init__.py
flipy/flipy/flipy/lp_constraint.py
flipy/flipy/flipy/lp_expression.py
flipy/flipy/flipy/lp_objective.py
flipy/flipy/flipy/lp_problem.py
flipy/flipy/flipy/lp_reader.py
flipy/flipy/flipy/lp_variable.py
flipy/flipy/flipy/utils.py
flipy/flipy/flipy/flipy/__init__.py
flipy/flipy/flipy/flipy/lp_constraint.py
flipy/flipy/flipy/flipy/lp_expression.py
flipy/flipy/flipy/flipy/lp_objective.py
flipy/flipy/flipy/flipy/lp_problem.py
flipy/flipy/flipy/flipy/lp_reader.py
flipy/flipy/flipy/flipy/lp_variable.py
flipy/flipy/flipy/flipy/utils.py
flipy/flipy/flipy/flipy/flipy/__init__.py
flipy/flipy/flipy/flipy/flipy/lp_constraint.py
flipy/flipy/flipy/flipy/flipy/lp_expression.py
flipy/flipy/flipy/flipy/flipy/lp_objective.py
flipy/flipy/flipy/flipy/flipy/lp_problem.py
flipy/flipy/flipy/flipy/flipy/lp_reader.py
flipy/flipy/flipy/flipy/flipy/lp_variable.py
flipy/flipy/flipy/flipy/flipy/utils.py
flipy/flipy/flipy/flipy/flipy/flipy/__init__.py
flipy/flipy/flipy/flipy/flipy/flipy/lp_constraint.py
flipy/flipy/flipy/flipy/flipy/flipy/lp_expression.py
flipy/flipy/flipy/flipy/flipy/flipy/lp_objective.py
flipy/flipy/flipy/flipy/flipy/flipy/lp_problem.py
flipy/flipy/flipy/flipy/flipy/flipy/lp_reader.py
flipy/flipy/flipy/flipy/flipy/flipy/lp_variable.py
flipy/flipy/flipy/flipy/flipy/flipy/utils.py
flipy/flipy/flipy/flipy/flipy/flipy/flipy/__init__.py
flipy/flipy/flipy/flipy/flipy/flipy/flipy/lp_constraint.py
flipy/flipy/flipy/flipy/flipy/flipy/flipy/lp_expression.py
flipy/flipy/flipy/flipy/flipy/flipy/flipy/lp_objective.py
flipy/flipy/flipy/flipy/flipy/flipy/flipy/lp_problem.py
flipy-0.0.5.dist-info/LICENSE
flipy-0.0.5.dist-info/METADATA
flipy-0.0.5.dist-info/WHEEL
flipy-0.0.5.dist-info/top_level.txt
flipy-0.0.5.dist-info/RECORD
