Metadata-Version: 2.1
Name: flipy
Version: 0.0.5
Summary: FreeWheel Linear Programming Interface for Python
Home-page: UNKNOWN
Author: FreeWheel
License: UNKNOWN
Platform: UNKNOWN
Classifier: Operating System :: Microsoft :: Windows
Classifier: Operating System :: MacOS :: MacOS X
Classifier: Operating System :: POSIX
Classifier: Natural Language :: English
Classifier: Programming Language :: Python :: 3.6
Classifier: Programming Language :: Python :: 3.7
Classifier: Programming Language :: Python :: 3.8
Classifier: Programming Language :: Python :: 3 :: Only
